[{"id":1,"name":"John","salary":40000,"department":"ETA","machineId":1001,"experience":"Technology Analyst"},{"id":2,"name":"Maria","salary":45000,"department":"IVS","experience":"Systems Engineer"},{"id":3,"name":"jack","salary":43000,"department":"ECSADM","machineId":1002,"experience":"Senior Systems Engineer"},{"id":4,"name":"Emily","salary":31000,"department":"DX","experience":"Senior Systems Engineer"},{"id":5,"name":"Steve","salary":51000,"department":"SGTSES","machineId":1003,"experience":"Senior Systems Engineer"},{"id":6,"name":"Stephen","salary":25000,"department":"DXEMP","experience":"Technology Analyst"},{"id":7,"name":"Kieron","salary":35000,"department":"IND","machineId":1004,"experience":"Technology Lead"},{"id":8,"name":"Kyle","salary":29000,"experience":"Systems Engineer"},{"id":9,"name":"Charles","salary":49000,"machineId":1005,"experience":"Manager"},{"id":10,"name":"Robin","salary":37000,"department":"DXEMP","experience":"Practice Lead"},{"id":11,"name":"Tom","salary":54000,"department":"IND","machineId":1006,"experience":"Technology Analyst / Manager"},{"id":12,"name":"Mark","salary":28000,"experience":"Systems Engineer"},{"id":13,"name":"Mike","salary":39000,"machineId":1007,"experience":"Systems Engineer"},{"id":14,"name":"Kasper chandu","salary":"100","department":"chill","machineId":"d123","experience":"Barking"},{"id":15,"name":"Mangoo Moti","salary":"12345","department":"Gayjapatti","machineId":"g33","experience":"Gossip"}]